core/__init__.py
core/build_treesitter.py
core/dashboard/.gitkeep
core/dashboard/__init__.py
core/dashboard/dashboard.py
core/dashboard/figure.py
core/dashboard/test_dashboard.py
core/main.py
core/metric/__init__.py
core/metric/metric.py
core/metric/result.py
core/metric/violation.py
core/qualitymodel/__init__.py
core/qualitymodel/qualitymodel.py
core/runner/__init__.py
core/runner/runner.py
core/runner/test_runner.py
core/source_repository/__init__.py
core/source_repository/file_info.py
core/source_repository/languages.py
core/source_repository/source_repository.py
core/source_repository/test/data/a_file.py
core/source_repository/test/data/a_nother_file.cs
core/source_repository/test_source_repository.py
core/util/.moduignore
core/writer/__init__.py
core/writer/test_writer.py
core/writer/writer.py
milkfrog-0.1.0.dist-info/LICENSE
milkfrog-0.1.0.dist-info/METADATA
milkfrog-0.1.0.dist-info/WHEEL
milkfrog-0.1.0.dist-info/entry_points.txt
milkfrog-0.1.0.dist-info/RECORD
