Metadata-Version: 2.1
Name: milkfrog
Version: 0.1.0
Summary: Prototyping a Quality Assessment Tool with Parameterized Quality Models
Author: Christoffer Gram
Author-email: chkg@itu.dk
Requires-Python: >=3.10,<4.0
Classifier: Programming Language :: Python :: 3
Classifier: Programming Language :: Python :: 3.10
Classifier: Programming Language :: Python :: 3.11
Requires-Dist: bokeh (>=3.0.3,<4.0.0)
Requires-Dist: chardet (>=5.1.0,<6.0.0)
Requires-Dist: click (>=8.1.3,<9.0.0)
Requires-Dist: defusedxml (>=0.7.1,<0.8.0)
Requires-Dist: tree-sitter (>=0.20.1,<0.21.0)
